pangee/__init__.py
pangee-0.1.0.dist-info/METADATA
pangee-0.1.0.dist-info/WHEEL
pangee-0.1.0.dist-info/top_level.txt
pangee-0.1.0.dist-info/RECORD
